{
  "cli": {
    "appVersionSource": "local"
  },
  "build": {
    "development": {
      "developmentClient": true,
      "distribution": "internal",
      "android": {
        "gradleCommand": ":app:assembleDebug"
      },
      "ios": {
        "simulator": true
      }
    },
    "production": {
      "developmentClient": false,
      "distribution": "store",
      "android": {
        "gradleCommand": ":app:assembleRelease"
      },
      "ios": {
        "simulator": false
      }
    }
  },
  "submit": {
    "production": {
      "android": {
        "serviceAccountKeyPath": "./credentials/android-service-account.json",
        "track": "internal"
      },
      "ios": {
        "appleId": "your-apple-id@example.com",
        "ascAppId": "your-app-store-connect-app-id"
      }
    }
  }
}